usercustomize.cpython-312-x86_64-linux-gnu.so
cms_enhance/common.cpython-312-x86_64-linux-gnu.so
cms_enhance/core.cpython-312-x86_64-linux-gnu.so
cms_enhance/message_hook.cpython-312-x86_64-linux-gnu.so
cms_enhance/sdk.cpython-312-x86_64-linux-gnu.so
cms_enhance/api/base.cpython-312-x86_64-linux-gnu.so
cms_enhance/api/nullbr.cpython-312-x86_64-linux-gnu.so
cms_enhance/api/open.cpython-312-x86_64-linux-gnu.so
cms_enhance/api/panso.cpython-312-x86_64-linux-gnu.so
cms_enhance-2026011903.dist-info/METADATA
cms_enhance-2026011903.dist-info/WHEEL
cms_enhance-2026011903.dist-info/top_level.txt
cms_enhance-2026011903.dist-info/RECORD
cms_enhance-2026011903.dist-info/licenses/LICENSE
