Metadata-Version: 2.4
Name: cms_enhance
Version: 2026011903
Summary: CMS Enhanced Module (Compiled Binary Only - No Source Code)
Author-email: iLay1678 <your.email@example.com>
License-Expression: MIT
Project-URL: Homepage, https://github.com/iLay1678/cloud-media-sync-enhanced
Project-URL: Repository, https://github.com/iLay1678/cloud-media-sync-enhanced.git
Project-URL: Issues, https://github.com/iLay1678/cloud-media-sync-enhanced/issues
Keywords: cms,enhancement,compiled,binary
Classifier: Development Status :: 4 - Beta
Classifier: Intended Audience :: Developers
Classifier: Programming Language :: Python :: 3
Classifier: Programming Language :: Python :: 3.12
Classifier: Programming Language :: Cython
Classifier: Topic :: Software Development :: Libraries :: Python Modules
Requires-Python: <3.13,>=3.12.0
License-File: LICENSE
Requires-Dist: nullbr>=1.0.8
Provides-Extra: dev
Requires-Dist: cython>=3.0.12; extra == "dev"
Requires-Dist: setuptools>=78.1.0; extra == "dev"
Requires-Dist: wheel; extra == "dev"
Requires-Dist: auditwheel; extra == "dev"
Dynamic: license-file
